LICENSE
MANIFEST.in
README.rst
requirements.txt
setup.py
django_kamasutra.egg-info/PKG-INFO
django_kamasutra.egg-info/SOURCES.txt
django_kamasutra.egg-info/dependency_links.txt
django_kamasutra.egg-info/top_level.txt
doc_src/api.rst
doc_src/getting_started.rst
doc_src/index.rst
doc_src/installation.rst
doc_src/_static/breadcrumb_background.png
doc_src/_static/default.css
doc_src/_static/documentation.png
doc_src/_static/header_sm_mid.png
doc_src/_static/scrn1.png
doc_src/_static/scrn2.png
doc_src/_static/searchfield_leftcap.png
doc_src/_static/searchfield_repeat.png
doc_src/_static/searchfield_rightcap.png
doc_src/_static/title_background.png
doc_src/_static/toc.js
doc_src/_static/triangle_closed.png
doc_src/_static/triangle_left.png
doc_src/_static/triangle_open.png
doc_src/_templates/layout.html
doc_src/reference/index.rst
doc_src/reference/render_content.rst
doc_src/reference/settings.rst
doc_src/reference/templatetags.rst
docs/api.html
docs/genindex.html
docs/getting_started.html
docs/index.html
docs/installation.html
docs/search.html
docs/searchindex.js
docs/_static/basic.css
docs/_static/breadcrumb_background.png
docs/_static/default.css
docs/_static/doctools.js
docs/_static/documentation.png
docs/_static/file.png
docs/_static/header_sm_mid.png
docs/_static/jquery.js
docs/_static/minus.png
docs/_static/plus.png
docs/_static/pygments.css
docs/_static/scrn1.png
docs/_static/scrn2.png
docs/_static/searchfield_leftcap.png
docs/_static/searchfield_repeat.png
docs/_static/searchfield_rightcap.png
docs/_static/searchtools.js
docs/_static/sidebar.js
docs/_static/title_background.png
docs/_static/toc.js
docs/_static/triangle_closed.png
docs/_static/triangle_left.png
docs/_static/triangle_open.png
docs/_static/underscore.js
docs/reference/index.html
docs/reference/models.html
docs/reference/render_content.html
docs/reference/settings.html
docs/reference/templatetags.html
positions/__init__.py
positions/admin.py
positions/fields.py
positions/forms.py
positions/models.py
positions/settings.py
positions/tests.py
positions/urls.py
positions/views.py
positions/fixtures/test_data.json
