Metadata-Version: 1.1
Name: django-kamasutra
Version: 0.2.11
Summary: A application to position objects anywhere on a page.
Home-page: https://github.com/callowayproject/django-kamasutra
Author: Jose Soares
Author-email: josefsoares@gmail.com
License: UNKNOWN
Platform: UNKNOWN
Classifier: Framework :: Django
Classifier: License :: OSI Approved :: Apache Software License
Classifier: Programming Language :: Python
